{
"companyName": "Unboxing Solutions",
"productName": "Wosta",
"productVersion": "1.3",
"dataUrl": "Websta.data.unityweb",
"wasmCodeUrl": "Websta.wasm.code.unityweb",
"wasmFrameworkUrl": "Websta.wasm.framework.unityweb",
"graphicsAPI": ["WebGL 2.0","WebGL 1.0"],
"webglContextAttributes": {"preserveDrawingBuffer": false},
"splashScreenStyle": "Dark",
"backgroundColor": "#285380",
"cacheControl": {"default": "must-revalidate"},
"developmentBuild": false,
"multithreading": false,
"unityVersion": "2019.2.0f1"
}